mycalc/calculator.py
knyjs-1.0.1.dist-info/METADATA
knyjs-1.0.1.dist-info/WHEEL
knyjs-1.0.1.dist-info/top_level.txt
knyjs-1.0.1.dist-info/RECORD
